[
  {
    "id": "exporter_mongodb_linux",
    "name": "Mongodb-Exporter",
    "controller_default_run": false,
    "icon": "",
    "node_operating_system": "linux",
    "service_type": "exec",
    "executable_path": "/opt/fusion-collectors/bin/mongodb_exporter",
    "execute_parameters": "--mongodb.host $MONGODB_HOST --mongodb.port $MONGODB_PORT --web.listen-address 127.0.0.1:$LISTEN_PORT",
    "validation_parameters": "",
    "default_template": "",
    "introduction": "Mongodb Exporter is a monitoring tool that collects and exports MongoDB metrics, providing insights into database performance and health."
  }
]

